{
    "module": "N/crypto/random",
    "description": "Cryptographically-secure pseudorandom generator methods for generating random bytes, integers, and UUIDs.",
    "supportedIn": ["client", "server"],
    "methods": [
        {
            "name": "generateBytes",
            "description": "Generates a cryptographically strong pseudorandom set of bytes.",
            "params": [
                { "name": "options", "type": "Object", "description": "Options" },
                { "name": "options.size", "type": "number", "description": "Number of random bytes to generate" }
            ],
            "returns": "Uint8Array"
        },
        {
            "name": "generateInt",
            "description": "Generates a cryptographically strong pseudorandom integer.",
            "params": [
                { "name": "options", "type": "Object", "description": "Options" },
                { "name": "options.max", "type": "number", "description": "End of random range (exclusive)" },
                { "name": "options.min", "type": "number", "description": "Start of random range. Default is 0.", "optional": true }
            ],
            "returns": "number"
        },
        {
            "name": "generateUUID",
            "description": "Generates a v4 Universally Unique Identifier (UUID) using a cryptographically secure random number generator.",
            "params": [],
            "returns": "string"
        }
    ],
    "enums": [],
    "objectTypes": []
}
